wiki_markdown.py
wiki_markdown-1.0.dist-info/RECORD
wiki_markdown-1.0.dist-info/WHEEL
wiki_markdown-1.0.dist-info/DESCRIPTION.rst
wiki_markdown-1.0.dist-info/metadata.json
wiki_markdown-1.0.dist-info/METADATA
wiki_markdown-1.0.dist-info/top_level.txt
