Metadata-Version: 2.0
Name: wiki-markdown
Version: 1.0
Summary: Markdown extension for AfricanaWiki
Home-page: https://rdugue@bitbucket.org/rdugue/
Author: Ralph Dugue
Author-email: rdugue1@gmail.com
License: UNKNOWN
Platform: UNKNOWN
Requires-Dist: markdown (>=2.5)
